stacks/__init__.py
stacks/command.py
stacks/config.py
stacks/stack.py
stacks/commands/__init__.py
stacks/commands/assume_role.py
stacks/commands/container_shell.py
stacks/commands/stack_details.py
stacks/commands/stack_launch.py
stacks/commands/stack_update.py
stacks/test/__init__.py
stacks/test/test_config.py
stacks/test/test_stack.py
stackedup-0.0.15.dist-info/LICENSE
stackedup-0.0.15.dist-info/METADATA
stackedup-0.0.15.dist-info/WHEEL
stackedup-0.0.15.dist-info/entry_points.txt
stackedup-0.0.15.dist-info/top_level.txt
stackedup-0.0.15.dist-info/RECORD
