Metadata-Version: 2.2
Name: stackedup
Version: 0.0.15
Summary: Tooling to help manage CloudFormation stacks
Home-page: https://github.com/ombu/stacks
Author: OMBU
Author-email: martin@ombuweb.com
Classifier: Programming Language :: Python :: 3
Classifier: License :: OSI Approved :: MIT License
Classifier: Operating System :: OS Independent
Requires-Python: >=3.9
License-File: LICENSE
Requires-Dist: boto3>=1.34.53
Requires-Dist: tabulate>=0.9.0
Requires-Dist: PyYaml>=6.0.1
Requires-Dist: awscliv2
Dynamic: author
Dynamic: author-email
Dynamic: classifier
Dynamic: description
Dynamic: description-content-type
Dynamic: home-page
Dynamic: requires-dist
Dynamic: requires-python
Dynamic: summary
